nostromo/__init__.py
nostromo/app.py
nostromo/injector.py
nostromo/models/__init__.py
nostromo/models/pipeline.py
nostromo/protocols/__init__.py
nostromo/protocols/executor.py
nostromo/protocols/path.py
nostromo/protocols/pipeline_editor.py
nostromo/protocols/pipelines.py
nostromo/protocols/ui_log.py
nostromo/run.py
nostromo/screens/__init__.py
nostromo/screens/logs.py
nostromo/services/__init__.py
nostromo/services/local_path.py
nostromo/services/pypyr_pipelines.py
nostromo/services/redis_executor.py
nostromo/services/redis_pipeline_storage.py
nostromo/services/rich_ui_log.py
nostromo/tabs/__init__.py
nostromo/tabs/pipeline_editor.py
nostromo/tabs/pipelines.py
nostromo/tcss.py
nostromo/widgets/__init__.py
nostromo/widgets/default_option_list.py
nostromo/widgets/horizontal_form.py
nostromo/widgets/pipeline_builder.py
nostromo-0.dev1.dist-info/LICENSE
nostromo-0.dev1.dist-info/METADATA
nostromo-0.dev1.dist-info/WHEEL
nostromo-0.dev1.dist-info/entry_points.txt
nostromo-0.dev1.dist-info/RECORD
